Workbook
Name Scenario_idx: Scenarios!$C$4
Name list_pepm_1: Inputs!$C$6
Name list_pepm_2: Inputs!$C$7
Name list_pepm_3: Inputs!$C$8
Name discount: Inputs!$C$9
Name hc_1: Inputs!$C$10
Name hc_2: Inputs!$C$11
Name hc_3: Inputs!$C$12
Name mix_1: Inputs!$C$13
Name mix_2: Inputs!$C$14
Name mix_3: Inputs!$C$15
Name mix_check: Inputs!$C$16
Name visitors_m1: Inputs!$C$18
Name visitor_growth: Inputs!$C$19
Name v2s: Inputs!$C$20
Name s2d: Inputs!$C$21
Name show_rate: Inputs!$C$22
Name held2trial: Inputs!$C$23
Name trial2paid: Inputs!$C$24
Name cpv: Inputs!$C$26
Name cost_per_demo: Inputs!$C$27
Name gm: Inputs!$C$28
Name churn: Inputs!$C$30
Name expansion: Inputs!$C$31
Name horizon: Inputs!$C$33
Name lever_step: Inputs!$C$34
Name ARPA_1: 'Unit Economics'!$F$5
Name ARPA_2: 'Unit Economics'!$F$6
Name ARPA_3: 'Unit Economics'!$F$7
Name ARPA: 'Unit Economics'!$B$11
Name GP_acct: 'Unit Economics'!$B$12
Name conv_v2p: 'Unit Economics'!$B$13
Name held2paid: 'Unit Economics'!$B$14
Name cost_per_visitor: 'Unit Economics'!$B$15
Name CAC: 'Unit Economics'!$B$16
Name CAC_check: 'Unit Economics'!$B$17
Name r_month: 'Unit Economics'!$B$18
Name Lifetime_months: 'Unit Economics'!$B$19
Name LTV: 'Unit Economics'!$B$20
Name LTV_CAC: 'Unit Economics'!$B$21
Name LTV_simple: 'Unit Economics'!$B$22
Name LTV_CAC_simple: 'Unit Economics'!$B$23
Name Payback: 'Unit Economics'!$B$24
Name NRR12: 'Unit Economics'!$B$25
Name GRR12: 'Unit Economics'!$B$26
Name MRR24: 'Unit Economics'!$B$27
Name Cust24: 'Unit Economics'!$B$28

Sheet README
A1: HR SaaS unit economics and funnel model
A2: Question: for an Indian SMB payroll/HR SaaS priced per employee per month, which lever moves LTV:CAC most?
A3: Independent portfolio project. Not affiliated with any company named. All figures are assumptions or public benchmarks, not company data.
A5: How to use
A6: 1. Pick Bear, Base or Bull in Scenarios!C3. Every sheet updates.
A7: 2. Change any blue number in Inputs (or the scenario table) to test your own assumptions.
A8: 3. Read results in Unit Economics. Sensitivity shows which lever matters most.
A9: 4. Customer counts are expected values, so fractions are normal.
A11: Colour legend
A12: Blue font = input you can change
A13: Black font = formula; do not overwrite
A15: Sheets
... A26: 12-month NRR = revenue from a cohort after 12 months / starting revenue (includes churned accounts and expansion).

Sheet Inputs
A1: Inputs
A2: Blue = hard input. Black = pulled from the active scenario (edit those on Scenarios). Sources in README.md.
A4: Parameter | B4: Unit | C4: Value | D4: Source / rationale
A5: Pricing and segments
A6: List price, 10-25 employees | B6: ₹/employee/month | C6: 120 | D6: Assumption within the public India range (per employee per month): Asanify ₹99-199; Keka ₹90-150 per extra employee (third-party report); RazorpayX ₹150 per extra employee; greytHR ₹45-85 and Zoho ₹40-100 per extra employee.
A7: List price, 26-100 employees | B7: ₹/employee/month | C7: 100 | D7: Assumption: lower rate for larger accounts, mirroring tiered pricing where extra employees cost less than the base block (greytHR, Keka, Zoho).
A8: List price, 101-500 employees | B8: ₹/employee/month | C8: 80 | D8: Assumption: as above.
A9: Discount off list price | B9: % of list | C9: =INDEX(Scenarios!$C$10:$E$10,1,Scenario_idx) | D9: From Scenarios.
A10: Average headcount, 10-25 segment | B10: employees | C10: 17 | D10: Assumption: below the midpoint because firm sizes skew small.
A11: Average headcount, 26-100 segment | B11: employees | C11: 55 | D11: Assumption: as above.
A12: Average headcount, 101-500 segment | B12: employees | C12: 220 | D12: Assumption: as above.
A13: New-customer mix, 10-25 | B13: % of new customers | C13: 0.55 | D13: Assumption. No verified public data on segment mix. Mix must total 100%.
A14: New-customer mix, 26-100 | B14: % of new customers | C14: 0.35 | D14: Assumption.
A15: New-customer mix, 101-500 | B15: % of new customers | C15: 0.1 | D15: Assumption.
A16: Mix check (must be 100%) | B16: % | C16: =mix_1+mix_2+mix_3 | D16: Formula.
A17: Funnel (monthly)
A18: Website visitors, month 1 | B18: visitors | C18: 40000 | D18: Assumption: illustrative scale. Volume changes MRR, not LTV:CAC.
A19: Visitor growth | B19: % per month | C19: 0.03 | D19: Assumption.
A20: Visitor to sign-up | B20: % | C20: 0.023 | D20: Benchmark: First Page Sage, B2B SaaS visitor-to-lead, small-company buyers ($1M-$10M revenue).
A21: Sign-up to demo booked | B21: % | C21: 0.118 | D21: Benchmark-derived: First Page Sage lead-to-MQL 37% x MQL-to-SQL 32% (small companies). Treats SQL as demo booked.
A22: Demo booked to demo held | B22: % | C22: =INDEX(Scenarios!$C$11:$E$11,1,Scenario_idx) | D22: From Scenarios.
A23: Demo held to trial | B23: % | C23: 0.4 | D23: Benchmark: First Page Sage SQL-to-opportunity 40% (small companies). Treats opportunity as trial started.
A24: Trial to paid | B24: % | C24: =INDEX(Scenarios!$C$12:$E$12,1,Scenario_idx) | D24: From Scenarios.
A25: Costs
A26: Marketing cost per visitor | B26: ₹/visitor | C26: 10 | D26: Assumption: blended organic and paid traffic. Not verified. Replace with marketing spend / visitors.
A27: Sales cost per demo held | B27: ₹/demo held | C27: 3000 | D27: Assumption: one inside-sales rep at ~₹1.25 lakh/month loaded cost holding ~40 demos a month. Not verified.
A28: Gross margin | B28: % of revenue | C28: =INDEX(Scenarios!$C$13:$E$13,1,Scenario_idx) | D28: From Scenarios.
A29: Retention
A30: Monthly logo churn | B30: % of customers/month | C30: =INDEX(Scenarios!$C$8:$E$8,1,Scenario_idx) | D30: From Scenarios.
A31: Monthly seat expansion | B31: % per month | C31: =INDEX(Scenarios!$C$9:$E$9,1,Scenario_idx) | D31: From Scenarios.
A32: Model settings
A33: LTV horizon | B33: months | C33: 60 | D33: Assumption: a 5-year cap stops LTV exploding when expansion nears churn.
A34: Lever improvement for ranking | B34: % relative | C34: 0.2 | D34: Set by the question: every lever improved by the same relative amount.

Sheet Scenarios
A1: Scenarios
A3: Active scenario (choose) | C3: Base
A4: Scenario index (formula) | C4: =MATCH(C3,$C$7:$E$7,0)
A7: Driver | B7: Unit | C7: Bear | D7: Base | E7: Bull | F7: Why these values
A8: Monthly logo churn | B8: % of customers/month | C8: 0.05 | D8: 0.03 | E8: 0.02 | F8: Kalungi (2025) puts SMB SaaS at 3-7% a month. Base sits at the low end because payroll is costly to switch mid-year (assumption).
A9: Monthly seat expansion | B9: % headcount growth/month | C9: 0.005 | D9: 0.01 | E9: 0.015 | F9: Assumption. Employee growth at existing customers. No verified public figure for Indian SMBs.
A10: Discount off list price | B10: % of list | C10: 0.25 | D10: 0.15 | E10: 0.05 | F10: Base ~ annual billing with 2 months free (16.7%), offered by Asanify. Bear reflects advertised promotions (Asanify: up to 60% off select plans).
A11: Demo show rate (booked to held) | B11: % | C11: 0.55 | D11: 0.65 | E11: 0.8 | F11: Weak benchmark: GrowthSpree (vendor blog, 2026, no method disclosed) gives a 55-65% median and 75-85% top quartile. Base uses the top of the median range.
A12: Trial to paid | B12: % | C12: 0.227 | D12: 0.35 | E12: 0.46 | F12: Bear: First Page Sage HR-industry trial-to-paid 22.7%. Bull: First Page Sage opportunity-to-close 46% for small-company buyers. Base: midpoint (assumption).
A13: Gross margin | B13: % of revenue | C13: 0.7 | D13: 0.75 | E13: 0.8 | F13: SaaS Capital 2026 medians (% of ARR): hosting 5%, DevOps 4%, pro-services CoGS 5%, other CoGS 3%, support and success 9%. About 26% if all sit in cost of revenue.

Sheet Funnel
A1: 24-month funnel, customers and MRR (expected values)
A2: Customers who join in a month do not churn that month. MRR grows with seat expansion and falls with churn.
A3: Month | B3: Visitors | C3: Sign-ups | D3: Demos booked | E3: Demos held | F3: Trials | G3: New customers | H3: New 10-25 | I3: New 26-100 | J3: New 101-500 | K3: Active 10-25 | L3: Active 26-100 | M3: Active 101-500 | N3: Active total | O3: Cumulative acquired | P3: MRR 10-25 | Q3: MRR 26-100 | R3: MRR 101-500 | S3: MRR total | T3: S&M spend | U3: CAC (month)
A4: 1 | B4: =visitors_m1*(1+visitor_growth)^(A4-1) | C4: =B4*v2s | D4: =C4*s2d | E4: =D4*show_rate | F4: =E4*held2trial | G4: =F4*trial2paid | H4: =G4*mix_1 | I4: =G4*mix_2 | J4: =G4*mix_3 | K4: =H4 | L4: =I4 | M4: =J4 | N4: =SUM(K4:M4) | O4: =G4 | P4: =H4*ARPA_1 | Q4: =I4*ARPA_2 | R4: =J4*ARPA_3 | S4: =SUM(P4:R4) | T4: =B4*cpv+E4*cost_per_demo | U4: =T4/G4
A5: 2 | B5: =visitors_m1*(1+visitor_growth)^(A5-1) | C5: =B5*v2s | D5: =C5*s2d | E5: =D5*show_rate | F5: =E5*held2trial | G5: =F5*trial2paid | H5: =G5*mix_1 | I5: =G5*mix_2 | J5: =G5*mix_3 | K5: =K4*(1-churn)+H5 | L5: =L4*(1-churn)+I5 | M5: =M4*(1-churn)+J5 | N5: =SUM(K5:M5) | O5: =O4+G5 | P5: =P4*(1-churn)*(1+expansion)+H5*ARPA_1 | Q5: =Q4*(1-churn)*(1+expansion)+I5*ARPA_2 | R5: =R4*(1-churn)*(1+expansion)+J5*ARPA_3 | S5: =SUM(P5:R5) | T5: =B5*cpv+E5*cost_per_demo | U5: =T5/G5
A6: 3 | B6: =visitors_m1*(1+visitor_growth)^(A6-1) | C6: =B6*v2s | D6: =C6*s2d | E6: =D6*show_rate | F6: =E6*held2trial | G6: =F6*trial2paid | H6: =G6*mix_1 | I6: =G6*mix_2 | J6: =G6*mix_3 | K6: =K5*(1-churn)+H6 | L6: =L5*(1-churn)+I6 | M6: =M5*(1-churn)+J6 | N6: =SUM(K6:M6) | O6: =O5+G6 | P6: =P5*(1-churn)*(1+expansion)+H6*ARPA_1 | Q6: =Q5*(1-churn)*(1+expansion)+I6*ARPA_2 | R6: =R5*(1-churn)*(1+expansion)+J6*ARPA_3 | S6: =SUM(P6:R6) | T6: =B6*cpv+E6*cost_per_demo | U6: =T6/G6
A7: 4 | B7: =visitors_m1*(1+visitor_growth)^(A7-1) | C7: =B7*v2s | D7: =C7*s2d | E7: =D7*show_rate | F7: =E7*held2trial | G7: =F7*trial2paid | H7: =G7*mix_1 | I7: =G7*mix_2 | J7: =G7*mix_3 | K7: =K6*(1-churn)+H7 | L7: =L6*(1-churn)+I7 | M7: =M6*(1-churn)+J7 | N7: =SUM(K7:M7) | O7: =O6+G7 | P7: =P6*(1-churn)*(1+expansion)+H7*ARPA_1 | Q7: =Q6*(1-churn)*(1+expansion)+I7*ARPA_2 | R7: =R6*(1-churn)*(1+expansion)+J7*ARPA_3 | S7: =SUM(P7:R7) | T7: =B7*cpv+E7*cost_per_demo | U7: =T7/G7
A8: 5 | B8: =visitors_m1*(1+visitor_growth)^(A8-1) | C8: =B8*v2s | D8: =C8*s2d | E8: =D8*show_rate | F8: =E8*held2trial | G8: =F8*trial2paid | H8: =G8*mix_1 | I8: =G8*mix_2 | J8: =G8*mix_3 | K8: =K7*(1-churn)+H8 | L8: =L7*(1-churn)+I8 | M8: =M7*(1-churn)+J8 | N8: =SUM(K8:M8) | O8: =O7+G8 | P8: =P7*(1-churn)*(1+expansion)+H8*ARPA_1 | Q8: =Q7*(1-churn)*(1+expansion)+I8*ARPA_2 | R8: =R7*(1-churn)*(1+expansion)+J8*ARPA_3 | S8: =SUM(P8:R8) | T8: =B8*cpv+E8*cost_per_demo | U8: =T8/G8
A9: 6 | B9: =visitors_m1*(1+visitor_growth)^(A9-1) | C9: =B9*v2s | D9: =C9*s2d | E9: =D9*show_rate | F9: =E9*held2trial | G9: =F9*trial2paid | H9: =G9*mix_1 | I9: =G9*mix_2 | J9: =G9*mix_3 | K9: =K8*(1-churn)+H9 | L9: =L8*(1-churn)+I9 | M9: =M8*(1-churn)+J9 | N9: =SUM(K9:M9) | O9: =O8+G9 | P9: =P8*(1-churn)*(1+expansion)+H9*ARPA_1 | Q9: =Q8*(1-churn)*(1+expansion)+I9*ARPA_2 | R9: =R8*(1-churn)*(1+expansion)+J9*ARPA_3 | S9: =SUM(P9:R9) | T9: =B9*cpv+E9*cost_per_demo | U9: =T9/G9
A10: 7 | B10: =visitors_m1*(1+visitor_growth)^(A10-1) | C10: =B10*v2s | D10: =C10*s2d | E10: =D10*show_rate | F10: =E10*held2trial | G10: =F10*trial2paid | H10: =G10*mix_1 | I10: =G10*mix_2 | J10: =G10*mix_3 | K10: =K9*(1-churn)+H10 | L10: =L9*(1-churn)+I10 | M10: =M9*(1-churn)+J10 | N10: =SUM(K10:M10) | O10: =O9+G10 | P10: =P9*(1-churn)*(1+expansion)+H10*ARPA_1 | Q10: =Q9*(1-churn)*(1+expansion)+I10*ARPA_2 | R10: =R9*(1-churn)*(1+expansion)+J10*ARPA_3 | S10: =SUM(P10:R10) | T10: =B10*cpv+E10*cost_per_demo | U10: =T10/G10
A11: 8 | B11: =visitors_m1*(1+visitor_growth)^(A11-1) | C11: =B11*v2s | D11: =C11*s2d | E11: =D11*show_rate | F11: =E11*held2trial | G11: =F11*trial2paid | H11: =G11*mix_1 | I11: =G11*mix_2 | J11: =G11*mix_3 | K11: =K10*(1-churn)+H11 | L11: =L10*(1-churn)+I11 | M11: =M10*(1-churn)+J11 | N11: =SUM(K11:M11) | O11: =O10+G11 | P11: =P10*(1-churn)*(1+expansion)+H11*ARPA_1 | Q11: =Q10*(1-churn)*(1+expansion)+I11*ARPA_2 | R11: =R10*(1-churn)*(1+expansion)+J11*ARPA_3 | S11: =SUM(P11:R11) | T11: =B11*cpv+E11*cost_per_demo | U11: =T11/G11
A12: 9 | B12: =visitors_m1*(1+visitor_growth)^(A12-1) | C12: =B12*v2s | D12: =C12*s2d | E12: =D12*show_rate | F12: =E12*held2trial | G12: =F12*trial2paid | H12: =G12*mix_1 | I12: =G12*mix_2 | J12: =G12*mix_3 | K12: =K11*(1-churn)+H12 | L12: =L11*(1-churn)+I12 | M12: =M11*(1-churn)+J12 | N12: =SUM(K12:M12) | O12: =O11+G12 | P12: =P11*(1-churn)*(1+expansion)+H12*ARPA_1 | Q12: =Q11*(1-churn)*(1+expansion)+I12*ARPA_2 | R12: =R11*(1-churn)*(1+expansion)+J12*ARPA_3 | S12: =SUM(P12:R12) | T12: =B12*cpv+E12*cost_per_demo | U12: =T12/G12
A13: 10 | B13: =visitors_m1*(1+visitor_growth)^(A13-1) | C13: =B13*v2s | D13: =C13*s2d | E13: =D13*show_rate | F13: =E13*held2trial | G13: =F13*trial2paid | H13: =G13*mix_1 | I13: =G13*mix_2 | J13: =G13*mix_3 | K13: =K12*(1-churn)+H13 | L13: =L12*(1-churn)+I13 | M13: =M12*(1-churn)+J13 | N13: =SUM(K13:M13) | O13: =O12+G13 | P13: =P12*(1-churn)*(1+expansion)+H13*ARPA_1 | Q13: =Q12*(1-churn)*(1+expansion)+I13*ARPA_2 | R13: =R12*(1-churn)*(1+expansion)+J13*ARPA_3 | S13: =SUM(P13:R13) | T13: =B13*cpv+E13*cost_per_demo | U13: =T13/G13
A14: 11 | B14: =visitors_m1*(1+visitor_growth)^(A14-1) | C14: =B14*v2s | D14: =C14*s2d | E14: =D14*show_rate | F14: =E14*held2trial | G14: =F14*trial2paid | H14: =G14*mix_1 | I14: =G14*mix_2 | J14: =G14*mix_3 | K14: =K13*(1-churn)+H14 | L14: =L13*(1-churn)+I14 | M14: =M13*(1-churn)+J14 | N14: =SUM(K14:M14) | O14: =O13+G14 | P14: =P13*(1-churn)*(1+expansion)+H14*ARPA_1 | Q14: =Q13*(1-churn)*(1+expansion)+I14*ARPA_2 | R14: =R13*(1-churn)*(1+expansion)+J14*ARPA_3 | S14: =SUM(P14:R14) | T14: =B14*cpv+E14*cost_per_demo | U14: =T14/G14
A15: 12 | B15: =visitors_m1*(1+visitor_growth)^(A15-1) | C15: =B15*v2s | D15: =C15*s2d | E15: =D15*show_rate | F15: =E15*held2trial | G15: =F15*trial2paid | H15: =G15*mix_1 | I15: =G15*mix_2 | J15: =G15*mix_3 | K15: =K14*(1-churn)+H15 | L15: =L14*(1-churn)+I15 | M15: =M14*(1-churn)+J15 | N15: =SUM(K15:M15) | O15: =O14+G15 | P15: =P14*(1-churn)*(1+expansion)+H15*ARPA_1 | Q15: =Q14*(1-churn)*(1+expansion)+I15*ARPA_2 | R15: =R14*(1-churn)*(1+expansion)+J15*ARPA_3 | S15: =SUM(P15:R15) | T15: =B15*cpv+E15*cost_per_demo | U15: =T15/G15
A16: 13 | B16: =visitors_m1*(1+visitor_growth)^(A16-1) | C16: =B16*v2s | D16: =C16*s2d | E16: =D16*show_rate | F16: =E16*held2trial | G16: =F16*trial2paid | H16: =G16*mix_1 | I16: =G16*mix_2 | J16: =G16*mix_3 | K16: =K15*(1-churn)+H16 | L16: =L15*(1-churn)+I16 | M16: =M15*(1-churn)+J16 | N16: =SUM(K16:M16) | O16: =O15+G16 | P16: =P15*(1-churn)*(1+expansion)+H16*ARPA_1 | Q16: =Q15*(1-churn)*(1+expansion)+I16*ARPA_2 | R16: =R15*(1-churn)*(1+expansion)+J16*ARPA_3 | S16: =SUM(P16:R16) | T16: =B16*cpv+E16*cost_per_demo | U16: =T16/G16
... A27: 24 | B27: =visitors_m1*(1+visitor_growth)^(A27-1) | C27: =B27*v2s | D27: =C27*s2d | E27: =D27*show_rate | F27: =E27*held2trial | G27: =F27*trial2paid | H27: =G27*mix_1 | I27: =G27*mix_2 | J27: =G27*mix_3 | K27: =K26*(1-churn)+H27 | L27: =L26*(1-churn)+I27 | M27: =M26*(1-churn)+J27 | N27: =SUM(K27:M27) | O27: =O26+G27 | P27: =P26*(1-churn)*(1+expansion)+H27*ARPA_1 | Q27: =Q26*(1-churn)*(1+expansion)+I27*ARPA_2 | R27: =R26*(1-churn)*(1+expansion)+J27*ARPA_3 | S27: =SUM(P27:R27) | T27: =B27*cpv+E27*cost_per_demo | U27: =T27/G27
A28: Total | B28: =SUM(B4:B27) | C28: =SUM(C4:C27) | D28: =SUM(D4:D27) | E28: =SUM(E4:E27) | F28: =SUM(F4:F27) | G28: =SUM(G4:G27) | H28: =SUM(H4:H27) | I28: =SUM(I4:I27) | J28: =SUM(J4:J27) | T28: =SUM(T4:T27)

Sheet Unit Economics
A1: Unit economics (active scenario)
A2: ="Scenario: "&Scenarios!C3
A4: Segment | B4: Mix | C4: Avg headcount | D4: List PEPM | E4: Net PEPM | F4: ARPA (₹/month) | G4: LTV (₹) | H4: LTV:CAC
A5: 10-25 employees | B5: =mix_1 | C5: =hc_1 | D5: =list_pepm_1 | E5: =D5*(1-discount) | F5: =E5*C5 | G5: =F5*gm*Lifetime_months | H5: =G5/CAC
A6: 26-100 employees | B6: =mix_2 | C6: =hc_2 | D6: =list_pepm_2 | E6: =D6*(1-discount) | F6: =E6*C6 | G6: =F6*gm*Lifetime_months | H6: =G6/CAC
A7: 101-500 employees | B7: =mix_3 | C7: =hc_3 | D7: =list_pepm_3 | E7: =D7*(1-discount) | F7: =E7*C7 | G7: =F7*gm*Lifetime_months | H7: =G7/CAC
A8: Segment LTV:CAC uses one blended CAC; larger accounts likely cost more to win, so read it as an upper bound for 101-500.
A10: Metric | B10: Value | C10: Formula logic
A11: Blended ARPA (new customer) | B11: =SUMPRODUCT(B5:B7,F5:F7) | C11: Mix-weighted ARPA
A12: Gross profit per account per month | B12: =ARPA*gm | C12: ARPA x gross margin
A13: Visitor to paid | B13: =v2s*s2d*show_rate*held2trial*trial2paid | C13: Product of funnel rates
A14: Demo held to paid | B14: =held2trial*trial2paid | C14: Held to trial x trial to paid
A15: S&M cost per visitor | B15: =cpv+v2s*s2d*show_rate*cost_per_demo | C15: Marketing per visitor + sales cost of demos per visitor
A16: Blended CAC | B16: =cost_per_visitor/conv_v2p | C16: S&M cost per visitor / visitor-to-paid
A17: Check: 24-month S&M / new customers | B17: =Funnel!T28/Funnel!G28 | C17: Must equal blended CAC
A18: Monthly revenue retention factor | B18: =(1-churn)*(1+expansion) | C18: (1 - churn) x (1 + expansion)
A19: Expected paying months (capped) | B19: =IF(ABS(1-r_month)<0.000000001,horizon,(1-r_month^horizon)/(1-r_month)) | C19: Sum of r^t for t = 0 to horizon - 1
A20: LTV (with expansion, capped) | B20: =GP_acct*Lifetime_months | C20: Headline LTV
A21: LTV:CAC | B21: =LTV/CAC | C21: Headline ratio
A22: LTV, simple (GP / churn, no expansion, no cap) | B22: =GP_acct/churn | C22: Textbook formula, for comparison
A23: LTV:CAC, simple | B23: =LTV_simple/CAC | C23: For comparison
A24: CAC payback | B24: =CAC/GP_acct | C24: Months of gross profit to recover CAC
A25: 12-month net revenue retention | B25: =r_month^12 | C25: Cohort revenue after 12 months, incl. churn and expansion
A26: 12-month gross revenue retention | B26: =(1-churn)^12 | C26: Churn only
A27: MRR in month 24 | B27: =Funnel!S27 | C27: From Funnel
A28: Active customers in month 24 | B28: =Funnel!N27 | C28: From Funnel

Sheet Sensitivity
A1: Sensitivity (active scenario)
A3: 1. LTV:CAC by monthly churn (rows) and demo held-to-paid conversion (columns). Other inputs as in the active scenario. Blue axis values can be edited.
A5: Churn / held-to-paid | B5: 0.06 | C5: 0.08 | D5: 0.1 | E5: 0.12 | F5: 0.14 | G5: 0.16 | H5: 0.18 | I5: 0.2 | J5: 0.25 | K5: 0.3
A6: 0.015 | B6: =GP_acct*IF(ABS(1-((1-$A6)*(1+expansion)))<0.000000001,horizon,(1-((1-$A6)*(1+expansion))^horizon)/(1-((1-$A6)*(1+expansion))))/(cost_per_visitor/(v2s*s2d*show_rate*B$5)) | C6: =GP_acct*IF(ABS(1-((1-$A6)*(1+expansion)))<0.000000001,horizon,(1-((1-$A6)*(1+expansion))^horizon)/(1-((1-$A6)*(1+expansion))))/(cost_per_visitor/(v2s*s2d*show_rate*C$5)) | D6: =GP_acct*IF(ABS(1-((1-$A6)*(1+expansion)))<0.000000001,horizon,(1-((1-$A6)*(1+expansion))^horizon)/(1-((1-$A6)*(1+expansion))))/(cost_per_visitor/(v2s*s2d*show_rate*D$5)) | E6: =GP_acct*IF(ABS(1-((1-$A6)*(1+expansion)))<0.000000001,horizon,(1-((1-$A6)*(1+expansion))^horizon)/(1-((1-$A6)*(1+expansion))))/(cost_per_visitor/(v2s*s2d*show_rate*E$5)) | F6: =GP_acct*IF(ABS(1-((1-$A6)*(1+expansion)))<0.000000001,horizon,(1-((1-$A6)*(1+expansion))^horizon)/(1-((1-$A6)*(1+expansion))))/(cost_per_visitor/(v2s*s2d*show_rate*F$5)) | G6: =GP_acct*IF(ABS(1-((1-$A6)*(1+expansion)))<0.000000001,horizon,(1-((1-$A6)*(1+expansion))^horizon)/(1-((1-$A6)*(1+expansion))))/(cost_per_visitor/(v2s*s2d*show_rate*G$5)) | H6: =GP_acct*IF(ABS(1-((1-$A6)*(1+expansion)))<0.000000001,horizon,(1-((1-$A6)*(1+expansion))^horizon)/(1-((1-$A6)*(1+expansion))))/(cost_per_visitor/(v2s*s2d*show_rate*H$5)) | I6: =GP_acct*IF(ABS(1-((1-$A6)*(1+expansion)))<0.000000001,horizon,(1-((1-$A6)*(1+expansion))^horizon)/(1-((1-$A6)*(1+expansion))))/(cost_per_visitor/(v2s*s2d*show_rate*I$5)) | ... K6: =GP_acct*IF(ABS(1-((1-$A6)*(1+expansion)))<0.000000001,horizon,(1-((1-$A6)*(1+expansion))^horizon)/(1-((1-$A6)*(1+expansion))))/(cost_per_visitor/(v2s*s2d*show_rate*K$5))
A7: 0.02 | B7: =GP_acct*IF(ABS(1-((1-$A7)*(1+expansion)))<0.000000001,horizon,(1-((1-$A7)*(1+expansion))^horizon)/(1-((1-$A7)*(1+expansion))))/(cost_per_visitor/(v2s*s2d*show_rate*B$5)) | C7: =GP_acct*IF(ABS(1-((1-$A7)*(1+expansion)))<0.000000001,horizon,(1-((1-$A7)*(1+expansion))^horizon)/(1-((1-$A7)*(1+expansion))))/(cost_per_visitor/(v2s*s2d*show_rate*C$5)) | D7: =GP_acct*IF(ABS(1-((1-$A7)*(1+expansion)))<0.000000001,horizon,(1-((1-$A7)*(1+expansion))^horizon)/(1-((1-$A7)*(1+expansion))))/(cost_per_visitor/(v2s*s2d*show_rate*D$5)) | E7: =GP_acct*IF(ABS(1-((1-$A7)*(1+expansion)))<0.000000001,horizon,(1-((1-$A7)*(1+expansion))^horizon)/(1-((1-$A7)*(1+expansion))))/(cost_per_visitor/(v2s*s2d*show_rate*E$5)) | F7: =GP_acct*IF(ABS(1-((1-$A7)*(1+expansion)))<0.000000001,horizon,(1-((1-$A7)*(1+expansion))^horizon)/(1-((1-$A7)*(1+expansion))))/(cost_per_visitor/(v2s*s2d*show_rate*F$5)) | G7: =GP_acct*IF(ABS(1-((1-$A7)*(1+expansion)))<0.000000001,horizon,(1-((1-$A7)*(1+expansion))^horizon)/(1-((1-$A7)*(1+expansion))))/(cost_per_visitor/(v2s*s2d*show_rate*G$5)) | H7: =GP_acct*IF(ABS(1-((1-$A7)*(1+expansion)))<0.000000001,horizon,(1-((1-$A7)*(1+expansion))^horizon)/(1-((1-$A7)*(1+expansion))))/(cost_per_visitor/(v2s*s2d*show_rate*H$5)) | I7: =GP_acct*IF(ABS(1-((1-$A7)*(1+expansion)))<0.000000001,horizon,(1-((1-$A7)*(1+expansion))^horizon)/(1-((1-$A7)*(1+expansion))))/(cost_per_visitor/(v2s*s2d*show_rate*I$5)) | ... K7: =GP_acct*IF(ABS(1-((1-$A7)*(1+expansion)))<0.000000001,horizon,(1-((1-$A7)*(1+expansion))^horizon)/(1-((1-$A7)*(1+expansion))))/(cost_per_visitor/(v2s*s2d*show_rate*K$5))
A8: 0.025 | B8: =GP_acct*IF(ABS(1-((1-$A8)*(1+expansion)))<0.000000001,horizon,(1-((1-$A8)*(1+expansion))^horizon)/(1-((1-$A8)*(1+expansion))))/(cost_per_visitor/(v2s*s2d*show_rate*B$5)) | C8: =GP_acct*IF(ABS(1-((1-$A8)*(1+expansion)))<0.000000001,horizon,(1-((1-$A8)*(1+expansion))^horizon)/(1-((1-$A8)*(1+expansion))))/(cost_per_visitor/(v2s*s2d*show_rate*C$5)) | D8: =GP_acct*IF(ABS(1-((1-$A8)*(1+expansion)))<0.000000001,horizon,(1-((1-$A8)*(1+expansion))^horizon)/(1-((1-$A8)*(1+expansion))))/(cost_per_visitor/(v2s*s2d*show_rate*D$5)) | E8: =GP_acct*IF(ABS(1-((1-$A8)*(1+expansion)))<0.000000001,horizon,(1-((1-$A8)*(1+expansion))^horizon)/(1-((1-$A8)*(1+expansion))))/(cost_per_visitor/(v2s*s2d*show_rate*E$5)) | F8: =GP_acct*IF(ABS(1-((1-$A8)*(1+expansion)))<0.000000001,horizon,(1-((1-$A8)*(1+expansion))^horizon)/(1-((1-$A8)*(1+expansion))))/(cost_per_visitor/(v2s*s2d*show_rate*F$5)) | G8: =GP_acct*IF(ABS(1-((1-$A8)*(1+expansion)))<0.000000001,horizon,(1-((1-$A8)*(1+expansion))^horizon)/(1-((1-$A8)*(1+expansion))))/(cost_per_visitor/(v2s*s2d*show_rate*G$5)) | H8: =GP_acct*IF(ABS(1-((1-$A8)*(1+expansion)))<0.000000001,horizon,(1-((1-$A8)*(1+expansion))^horizon)/(1-((1-$A8)*(1+expansion))))/(cost_per_visitor/(v2s*s2d*show_rate*H$5)) | I8: =GP_acct*IF(ABS(1-((1-$A8)*(1+expansion)))<0.000000001,horizon,(1-((1-$A8)*(1+expansion))^horizon)/(1-((1-$A8)*(1+expansion))))/(cost_per_visitor/(v2s*s2d*show_rate*I$5)) | ... K8: =GP_acct*IF(ABS(1-((1-$A8)*(1+expansion)))<0.000000001,horizon,(1-((1-$A8)*(1+expansion))^horizon)/(1-((1-$A8)*(1+expansion))))/(cost_per_visitor/(v2s*s2d*show_rate*K$5))
A9: 0.03 | B9: =GP_acct*IF(ABS(1-((1-$A9)*(1+expansion)))<0.000000001,horizon,(1-((1-$A9)*(1+expansion))^horizon)/(1-((1-$A9)*(1+expansion))))/(cost_per_visitor/(v2s*s2d*show_rate*B$5)) | C9: =GP_acct*IF(ABS(1-((1-$A9)*(1+expansion)))<0.000000001,horizon,(1-((1-$A9)*(1+expansion))^horizon)/(1-((1-$A9)*(1+expansion))))/(cost_per_visitor/(v2s*s2d*show_rate*C$5)) | D9: =GP_acct*IF(ABS(1-((1-$A9)*(1+expansion)))<0.000000001,horizon,(1-((1-$A9)*(1+expansion))^horizon)/(1-((1-$A9)*(1+expansion))))/(cost_per_visitor/(v2s*s2d*show_rate*D$5)) | E9: =GP_acct*IF(ABS(1-((1-$A9)*(1+expansion)))<0.000000001,horizon,(1-((1-$A9)*(1+expansion))^horizon)/(1-((1-$A9)*(1+expansion))))/(cost_per_visitor/(v2s*s2d*show_rate*E$5)) | F9: =GP_acct*IF(ABS(1-((1-$A9)*(1+expansion)))<0.000000001,horizon,(1-((1-$A9)*(1+expansion))^horizon)/(1-((1-$A9)*(1+expansion))))/(cost_per_visitor/(v2s*s2d*show_rate*F$5)) | G9: =GP_acct*IF(ABS(1-((1-$A9)*(1+expansion)))<0.000000001,horizon,(1-((1-$A9)*(1+expansion))^horizon)/(1-((1-$A9)*(1+expansion))))/(cost_per_visitor/(v2s*s2d*show_rate*G$5)) | H9: =GP_acct*IF(ABS(1-((1-$A9)*(1+expansion)))<0.000000001,horizon,(1-((1-$A9)*(1+expansion))^horizon)/(1-((1-$A9)*(1+expansion))))/(cost_per_visitor/(v2s*s2d*show_rate*H$5)) | I9: =GP_acct*IF(ABS(1-((1-$A9)*(1+expansion)))<0.000000001,horizon,(1-((1-$A9)*(1+expansion))^horizon)/(1-((1-$A9)*(1+expansion))))/(cost_per_visitor/(v2s*s2d*show_rate*I$5)) | ... K9: =GP_acct*IF(ABS(1-((1-$A9)*(1+expansion)))<0.000000001,horizon,(1-((1-$A9)*(1+expansion))^horizon)/(1-((1-$A9)*(1+expansion))))/(cost_per_visitor/(v2s*s2d*show_rate*K$5))
A10: 0.035 | B10: =GP_acct*IF(ABS(1-((1-$A10)*(1+expansion)))<0.000000001,horizon,(1-((1-$A10)*(1+expansion))^horizon)/(1-((1-$A10)*(1+expansion))))/(cost_per_visitor/(v2s*s2d*show_rate*B$5)) | C10: =GP_acct*IF(ABS(1-((1-$A10)*(1+expansion)))<0.000000001,horizon,(1-((1-$A10)*(1+expansion))^horizon)/(1-((1-$A10)*(1+expansion))))/(cost_per_visitor/(v2s*s2d*show_rate*C$5)) | D10: =GP_acct*IF(ABS(1-((1-$A10)*(1+expansion)))<0.000000001,horizon,(1-((1-$A10)*(1+expansion))^horizon)/(1-((1-$A10)*(1+expansion))))/(cost_per_visitor/(v2s*s2d*show_rate*D$5)) | E10: =GP_acct*IF(ABS(1-((1-$A10)*(1+expansion)))<0.000000001,horizon,(1-((1-$A10)*(1+expansion))^horizon)/(1-((1-$A10)*(1+expansion))))/(cost_per_visitor/(v2s*s2d*show_rate*E$5)) | F10: =GP_acct*IF(ABS(1-((1-$A10)*(1+expansion)))<0.000000001,horizon,(1-((1-$A10)*(1+expansion))^horizon)/(1-((1-$A10)*(1+expansion))))/(cost_per_visitor/(v2s*s2d*show_rate*F$5)) | G10: =GP_acct*IF(ABS(1-((1-$A10)*(1+expansion)))<0.000000001,horizon,(1-((1-$A10)*(1+expansion))^horizon)/(1-((1-$A10)*(1+expansion))))/(cost_per_visitor/(v2s*s2d*show_rate*G$5)) | H10: =GP_acct*IF(ABS(1-((1-$A10)*(1+expansion)))<0.000000001,horizon,(1-((1-$A10)*(1+expansion))^horizon)/(1-((1-$A10)*(1+expansion))))/(cost_per_visitor/(v2s*s2d*show_rate*H$5)) | I10: =GP_acct*IF(ABS(1-((1-$A10)*(1+expansion)))<0.000000001,horizon,(1-((1-$A10)*(1+expansion))^horizon)/(1-((1-$A10)*(1+expansion))))/(cost_per_visitor/(v2s*s2d*show_rate*I$5)) | ... K10: =GP_acct*IF(ABS(1-((1-$A10)*(1+expansion)))<0.000000001,horizon,(1-((1-$A10)*(1+expansion))^horizon)/(1-((1-$A10)*(1+expansion))))/(cost_per_visitor/(v2s*s2d*show_rate*K$5))
A11: 0.04 | B11: =GP_acct*IF(ABS(1-((1-$A11)*(1+expansion)))<0.000000001,horizon,(1-((1-$A11)*(1+expansion))^horizon)/(1-((1-$A11)*(1+expansion))))/(cost_per_visitor/(v2s*s2d*show_rate*B$5)) | C11: =GP_acct*IF(ABS(1-((1-$A11)*(1+expansion)))<0.000000001,horizon,(1-((1-$A11)*(1+expansion))^horizon)/(1-((1-$A11)*(1+expansion))))/(cost_per_visitor/(v2s*s2d*show_rate*C$5)) | D11: =GP_acct*IF(ABS(1-((1-$A11)*(1+expansion)))<0.000000001,horizon,(1-((1-$A11)*(1+expansion))^horizon)/(1-((1-$A11)*(1+expansion))))/(cost_per_visitor/(v2s*s2d*show_rate*D$5)) | E11: =GP_acct*IF(ABS(1-((1-$A11)*(1+expansion)))<0.000000001,horizon,(1-((1-$A11)*(1+expansion))^horizon)/(1-((1-$A11)*(1+expansion))))/(cost_per_visitor/(v2s*s2d*show_rate*E$5)) | F11: =GP_acct*IF(ABS(1-((1-$A11)*(1+expansion)))<0.000000001,horizon,(1-((1-$A11)*(1+expansion))^horizon)/(1-((1-$A11)*(1+expansion))))/(cost_per_visitor/(v2s*s2d*show_rate*F$5)) | G11: =GP_acct*IF(ABS(1-((1-$A11)*(1+expansion)))<0.000000001,horizon,(1-((1-$A11)*(1+expansion))^horizon)/(1-((1-$A11)*(1+expansion))))/(cost_per_visitor/(v2s*s2d*show_rate*G$5)) | H11: =GP_acct*IF(ABS(1-((1-$A11)*(1+expansion)))<0.000000001,horizon,(1-((1-$A11)*(1+expansion))^horizon)/(1-((1-$A11)*(1+expansion))))/(cost_per_visitor/(v2s*s2d*show_rate*H$5)) | I11: =GP_acct*IF(ABS(1-((1-$A11)*(1+expansion)))<0.000000001,horizon,(1-((1-$A11)*(1+expansion))^horizon)/(1-((1-$A11)*(1+expansion))))/(cost_per_visitor/(v2s*s2d*show_rate*I$5)) | ... K11: =GP_acct*IF(ABS(1-((1-$A11)*(1+expansion)))<0.000000001,horizon,(1-((1-$A11)*(1+expansion))^horizon)/(1-((1-$A11)*(1+expansion))))/(cost_per_visitor/(v2s*s2d*show_rate*K$5))
A12: 0.05 | B12: =GP_acct*IF(ABS(1-((1-$A12)*(1+expansion)))<0.000000001,horizon,(1-((1-$A12)*(1+expansion))^horizon)/(1-((1-$A12)*(1+expansion))))/(cost_per_visitor/(v2s*s2d*show_rate*B$5)) | C12: =GP_acct*IF(ABS(1-((1-$A12)*(1+expansion)))<0.000000001,horizon,(1-((1-$A12)*(1+expansion))^horizon)/(1-((1-$A12)*(1+expansion))))/(cost_per_visitor/(v2s*s2d*show_rate*C$5)) | D12: =GP_acct*IF(ABS(1-((1-$A12)*(1+expansion)))<0.000000001,horizon,(1-((1-$A12)*(1+expansion))^horizon)/(1-((1-$A12)*(1+expansion))))/(cost_per_visitor/(v2s*s2d*show_rate*D$5)) | E12: =GP_acct*IF(ABS(1-((1-$A12)*(1+expansion)))<0.000000001,horizon,(1-((1-$A12)*(1+expansion))^horizon)/(1-((1-$A12)*(1+expansion))))/(cost_per_visitor/(v2s*s2d*show_rate*E$5)) | F12: =GP_acct*IF(ABS(1-((1-$A12)*(1+expansion)))<0.000000001,horizon,(1-((1-$A12)*(1+expansion))^horizon)/(1-((1-$A12)*(1+expansion))))/(cost_per_visitor/(v2s*s2d*show_rate*F$5)) | G12: =GP_acct*IF(ABS(1-((1-$A12)*(1+expansion)))<0.000000001,horizon,(1-((1-$A12)*(1+expansion))^horizon)/(1-((1-$A12)*(1+expansion))))/(cost_per_visitor/(v2s*s2d*show_rate*G$5)) | H12: =GP_acct*IF(ABS(1-((1-$A12)*(1+expansion)))<0.000000001,horizon,(1-((1-$A12)*(1+expansion))^horizon)/(1-((1-$A12)*(1+expansion))))/(cost_per_visitor/(v2s*s2d*show_rate*H$5)) | I12: =GP_acct*IF(ABS(1-((1-$A12)*(1+expansion)))<0.000000001,horizon,(1-((1-$A12)*(1+expansion))^horizon)/(1-((1-$A12)*(1+expansion))))/(cost_per_visitor/(v2s*s2d*show_rate*I$5)) | ... K12: =GP_acct*IF(ABS(1-((1-$A12)*(1+expansion)))<0.000000001,horizon,(1-((1-$A12)*(1+expansion))^horizon)/(1-((1-$A12)*(1+expansion))))/(cost_per_visitor/(v2s*s2d*show_rate*K$5))
A13: 0.06 | B13: =GP_acct*IF(ABS(1-((1-$A13)*(1+expansion)))<0.000000001,horizon,(1-((1-$A13)*(1+expansion))^horizon)/(1-((1-$A13)*(1+expansion))))/(cost_per_visitor/(v2s*s2d*show_rate*B$5)) | C13: =GP_acct*IF(ABS(1-((1-$A13)*(1+expansion)))<0.000000001,horizon,(1-((1-$A13)*(1+expansion))^horizon)/(1-((1-$A13)*(1+expansion))))/(cost_per_visitor/(v2s*s2d*show_rate*C$5)) | D13: =GP_acct*IF(ABS(1-((1-$A13)*(1+expansion)))<0.000000001,horizon,(1-((1-$A13)*(1+expansion))^horizon)/(1-((1-$A13)*(1+expansion))))/(cost_per_visitor/(v2s*s2d*show_rate*D$5)) | E13: =GP_acct*IF(ABS(1-((1-$A13)*(1+expansion)))<0.000000001,horizon,(1-((1-$A13)*(1+expansion))^horizon)/(1-((1-$A13)*(1+expansion))))/(cost_per_visitor/(v2s*s2d*show_rate*E$5)) | F13: =GP_acct*IF(ABS(1-((1-$A13)*(1+expansion)))<0.000000001,horizon,(1-((1-$A13)*(1+expansion))^horizon)/(1-((1-$A13)*(1+expansion))))/(cost_per_visitor/(v2s*s2d*show_rate*F$5)) | G13: =GP_acct*IF(ABS(1-((1-$A13)*(1+expansion)))<0.000000001,horizon,(1-((1-$A13)*(1+expansion))^horizon)/(1-((1-$A13)*(1+expansion))))/(cost_per_visitor/(v2s*s2d*show_rate*G$5)) | H13: =GP_acct*IF(ABS(1-((1-$A13)*(1+expansion)))<0.000000001,horizon,(1-((1-$A13)*(1+expansion))^horizon)/(1-((1-$A13)*(1+expansion))))/(cost_per_visitor/(v2s*s2d*show_rate*H$5)) | I13: =GP_acct*IF(ABS(1-((1-$A13)*(1+expansion)))<0.000000001,horizon,(1-((1-$A13)*(1+expansion))^horizon)/(1-((1-$A13)*(1+expansion))))/(cost_per_visitor/(v2s*s2d*show_rate*I$5)) | ... K13: =GP_acct*IF(ABS(1-((1-$A13)*(1+expansion)))<0.000000001,horizon,(1-((1-$A13)*(1+expansion))^horizon)/(1-((1-$A13)*(1+expansion))))/(cost_per_visitor/(v2s*s2d*show_rate*K$5))
A14: 0.07 | B14: =GP_acct*IF(ABS(1-((1-$A14)*(1+expansion)))<0.000000001,horizon,(1-((1-$A14)*(1+expansion))^horizon)/(1-((1-$A14)*(1+expansion))))/(cost_per_visitor/(v2s*s2d*show_rate*B$5)) | C14: =GP_acct*IF(ABS(1-((1-$A14)*(1+expansion)))<0.000000001,horizon,(1-((1-$A14)*(1+expansion))^horizon)/(1-((1-$A14)*(1+expansion))))/(cost_per_visitor/(v2s*s2d*show_rate*C$5)) | D14: =GP_acct*IF(ABS(1-((1-$A14)*(1+expansion)))<0.000000001,horizon,(1-((1-$A14)*(1+expansion))^horizon)/(1-((1-$A14)*(1+expansion))))/(cost_per_visitor/(v2s*s2d*show_rate*D$5)) | E14: =GP_acct*IF(ABS(1-((1-$A14)*(1+expansion)))<0.000000001,horizon,(1-((1-$A14)*(1+expansion))^horizon)/(1-((1-$A14)*(1+expansion))))/(cost_per_visitor/(v2s*s2d*show_rate*E$5)) | F14: =GP_acct*IF(ABS(1-((1-$A14)*(1+expansion)))<0.000000001,horizon,(1-((1-$A14)*(1+expansion))^horizon)/(1-((1-$A14)*(1+expansion))))/(cost_per_visitor/(v2s*s2d*show_rate*F$5)) | G14: =GP_acct*IF(ABS(1-((1-$A14)*(1+expansion)))<0.000000001,horizon,(1-((1-$A14)*(1+expansion))^horizon)/(1-((1-$A14)*(1+expansion))))/(cost_per_visitor/(v2s*s2d*show_rate*G$5)) | H14: =GP_acct*IF(ABS(1-((1-$A14)*(1+expansion)))<0.000000001,horizon,(1-((1-$A14)*(1+expansion))^horizon)/(1-((1-$A14)*(1+expansion))))/(cost_per_visitor/(v2s*s2d*show_rate*H$5)) | I14: =GP_acct*IF(ABS(1-((1-$A14)*(1+expansion)))<0.000000001,horizon,(1-((1-$A14)*(1+expansion))^horizon)/(1-((1-$A14)*(1+expansion))))/(cost_per_visitor/(v2s*s2d*show_rate*I$5)) | ... K14: =GP_acct*IF(ABS(1-((1-$A14)*(1+expansion)))<0.000000001,horizon,(1-((1-$A14)*(1+expansion))^horizon)/(1-((1-$A14)*(1+expansion))))/(cost_per_visitor/(v2s*s2d*show_rate*K$5))
A16: Current scenario: churn | C16: =churn | D16: held-to-paid | F16: =held2paid | G16: LTV:CAC | H16: =LTV_CAC
A17: Colour: red below 1x, yellow at 3x, green at 5x and above.
A19: ="2. One lever at a time: each improved by "&TEXT(lever_step,"0%")&" (relative). Change the step in Inputs."
A20: Lever | B20: Price mult. | C20: Churn mult. | D20: Expansion mult. | E20: Visitor-to-sign-up mult. | F20: Held-to-paid mult. | G20: GP/account/month | H20: Retention factor | I20: LTV | J20: CAC | K20: LTV:CAC | L20: Change vs base | M20: Rank | N20: CAC payback (months)
A21: Base (no change) | B21: =1 | C21: =1 | D21: =1 | E21: =1 | F21: =1 | G21: =ARPA*B21*gm | H21: =(1-churn*C21)*(1+expansion*D21) | I21: =G21*IF(ABS(1-H21)<0.000000001,horizon,(1-H21^horizon)/(1-H21)) | J21: =(cpv+v2s*E21*s2d*show_rate*cost_per_demo)/(v2s*E21*s2d*show_rate*held2paid*F21) | K21: =I21/J21 | L21: =ROUND(K21/K$21-1,6) | N21: =J21/G21
A22: Price (PEPM) up | B22: =1+lever_step | C22: =1 | D22: =1 | E22: =1 | F22: =1 | G22: =ARPA*B22*gm | H22: =(1-churn*C22)*(1+expansion*D22) | I22: =G22*IF(ABS(1-H22)<0.000000001,horizon,(1-H22^horizon)/(1-H22)) | J22: =(cpv+v2s*E22*s2d*show_rate*cost_per_demo)/(v2s*E22*s2d*show_rate*held2paid*F22) | K22: =I22/J22 | L22: =ROUND(K22/K$21-1,6) | M22: =RANK(L22,$L$22:$L$26) | N22: =J22/G22
A23: Monthly churn down | B23: =1 | C23: =1-lever_step | D23: =1 | E23: =1 | F23: =1 | G23: =ARPA*B23*gm | H23: =(1-churn*C23)*(1+expansion*D23) | I23: =G23*IF(ABS(1-H23)<0.000000001,horizon,(1-H23^horizon)/(1-H23)) | J23: =(cpv+v2s*E23*s2d*show_rate*cost_per_demo)/(v2s*E23*s2d*show_rate*held2paid*F23) | K23: =I23/J23 | L23: =ROUND(K23/K$21-1,6) | M23: =RANK(L23,$L$22:$L$26) | N23: =J23/G23
A24: Seat expansion up | B24: =1 | C24: =1 | D24: =1+lever_step | E24: =1 | F24: =1 | G24: =ARPA*B24*gm | H24: =(1-churn*C24)*(1+expansion*D24) | I24: =G24*IF(ABS(1-H24)<0.000000001,horizon,(1-H24^horizon)/(1-H24)) | J24: =(cpv+v2s*E24*s2d*show_rate*cost_per_demo)/(v2s*E24*s2d*show_rate*held2paid*F24) | K24: =I24/J24 | L24: =ROUND(K24/K$21-1,6) | M24: =RANK(L24,$L$22:$L$26) | N24: =J24/G24
A25: Visitor-to-sign-up up (top of funnel) | B25: =1 | C25: =1 | D25: =1 | E25: =1+lever_step | F25: =1 | G25: =ARPA*B25*gm | H25: =(1-churn*C25)*(1+expansion*D25) | I25: =G25*IF(ABS(1-H25)<0.000000001,horizon,(1-H25^horizon)/(1-H25)) | J25: =(cpv+v2s*E25*s2d*show_rate*cost_per_demo)/(v2s*E25*s2d*show_rate*held2paid*F25) | K25: =I25/J25 | L25: =ROUND(K25/K$21-1,6) | M25: =RANK(L25,$L$22:$L$26) | N25: =J25/G25
A26: Demo held-to-paid up (bottom of funnel) | B26: =1 | C26: =1 | D26: =1 | E26: =1 | F26: =1+lever_step | G26: =ARPA*B26*gm | H26: =(1-churn*C26)*(1+expansion*D26) | I26: =G26*IF(ABS(1-H26)<0.000000001,horizon,(1-H26^horizon)/(1-H26)) | J26: =(cpv+v2s*E26*s2d*show_rate*cost_per_demo)/(v2s*E26*s2d*show_rate*held2paid*F26) | K26: =I26/J26 | L26: =ROUND(K26/K$21-1,6) | M26: =RANK(L26,$L$22:$L$26) | N26: =J26/G26
A28: Price rises assume no effect on conversion or churn. A price rise of the lever step is neutral on LTV:CAC if held-to-paid conversion falls by: | L28: =1-1/(1+lever_step)
A29: Churn does not change CAC payback; only price, gross margin and funnel costs do.
